MANIFEST.in
README.rst
setup.py
pyitect/__init__.py
pyitect/imports.py
pyitect/pyitect.py
pyitect.egg-info/PKG-INFO
pyitect.egg-info/SOURCES.txt
pyitect.egg-info/dependency_links.txt
pyitect.egg-info/requires.txt
pyitect.egg-info/top_level.txt
tests/__init__.py
tests/test.py
tests/plugins/bad_plugin/bad_plugin.json
tests/plugins/bad_plugin/bad_plugin.py
tests/plugins/component_subtype_plugin/component_subtype_plugin.json
tests/plugins/component_subtype_plugin/multiple_version.py
tests/plugins/consume_plugin/consume.py
tests/plugins/consume_plugin/consume_plugin.json
tests/plugins/on_enable_plugin/on_enable_plugin.json
tests/plugins/on_enable_plugin/plugin.py
tests/plugins/provide_plugin/provide.py
tests/plugins/provide_plugin/provide_plugin.json
tests/plugins/provide_pluginv2/provide.py
tests/plugins/provide_pluginv2/provide_pluginv2.json
tests/plugins/relative_plugin/__init__.py
tests/plugins/relative_plugin/relative_plugin.json
tests/plugins/relative_plugin/relative_test.py
tests/plugins/subtype_plugin/subtype.py
tests/plugins/subtype_plugin/subtype_plugin.json
tests/plugins/yaml_plugin/yaml_plugin.py