Metadata-Version: 1.1
Name: pyitect
Version: 2.0.1
Summary: A simple system for structuring a modeler project architecture via plugin like modules, uses the new importlib abilities first avalible in python 3.4, includes an exec load mode for support of python 3.0+
Home-page: https://github.com/Ryex/pyitect
Author: Benjamin "Ryex" Powers
Author-email: Ryexander+pyitect@gmail.com
License: ISC
Download-URL: https://pypi.python.org/pypi/pyitect/
Keywords: architect,project,modeler,module,plugin
Platform: UNKNOWN
Classifier: Development Status :: 4 - Beta
Classifier: Programming Language :: Python
Classifier: Programming Language :: Python :: 3
Classifier: Programming Language :: Python :: 3.2
Classifier: Programming Language :: Python :: 3.3
Classifier: Programming Language :: Python :: 3.4
Classifier: Programming Language :: Python :: 2
Classifier: Programming Language :: Python :: 2.6
Classifier: Programming Language :: Python :: 2.7
Classifier: License :: OSI Approved :: ISC License (ISCL)
Classifier: Intended Audience :: Developers
Classifier: Operating System :: OS Independent
Classifier: Topic :: Software Development :: Libraries :: Application Frameworks
